{
  "Logs": [
    {
      "Turn": 0,
      "Info": [
        "Successful player initialization"
      ],
      "Exception": []
    },
    {
      "Turn": 1,
      "Info": [
        "Finished game loop"
      ],
      "Exception": [
        "IllegalThreadStateException: Error while getting move action from player 1",
        "Stack Trace: java.lang.IllegalThreadStateException: read timed out",
        "\tat mech.mania.engine.networking.SafeBufferedReader.waitReady(SafeBufferedReader.java:112)",
        "\tat mech.mania.engine.networking.SafeBufferedReader.readLine(SafeBufferedReader.java:37)",
        "\tat mech.mania.engine.networking.PlayerCommunicationInfo.safeGetLine(PlayerCommunicationInfo.java:136)",
        "\tat mech.mania.engine.networking.PlayerCommunicationInfo.getPlayerDecision(PlayerCommunicationInfo.java:157)",
        "\tat mech.mania.engine.Main.gameLoop(Main.java:355)",
        "\tat mech.mania.engine.Main.main(Main.java:132)"
      ]
    }
  ]
}